LICENSE
MANIFEST.in
README.md
requirements.txt
setup.cfg
setup.py
vfxwindow/__init__.py
vfxwindow/application.py
vfxwindow/debug.py
vfxwindow/exceptions.py
vfxwindow.egg-info/PKG-INFO
vfxwindow.egg-info/SOURCES.txt
vfxwindow.egg-info/dependency_links.txt
vfxwindow.egg-info/requires.txt
vfxwindow.egg-info/top_level.txt
vfxwindow/abstract/__init__.py
vfxwindow/abstract/application.py
vfxwindow/abstract/callbacks.py
vfxwindow/abstract/gui.py
vfxwindow/blender/__init__.py
vfxwindow/blender/application.py
vfxwindow/blender/callbacks.py
vfxwindow/blender/gui.py
vfxwindow/cryengine/__init__.py
vfxwindow/cryengine/application.py
vfxwindow/cryengine/gui.py
vfxwindow/fusion/__init__.py
vfxwindow/fusion/application.py
vfxwindow/fusion/gui.py
vfxwindow/gaffer/__init__.py
vfxwindow/gaffer/application.py
vfxwindow/gaffer/gui.py
vfxwindow/houdini/__init__.py
vfxwindow/houdini/application.py
vfxwindow/houdini/callbacks.py
vfxwindow/houdini/gui.py
vfxwindow/katana/__init__.py
vfxwindow/katana/application.py
vfxwindow/katana/gui.py
vfxwindow/max/__init__.py
vfxwindow/max/application.py
vfxwindow/max/gui.py
vfxwindow/maya/__init__.py
vfxwindow/maya/application.py
vfxwindow/maya/callbacks.py
vfxwindow/maya/gui.py
vfxwindow/natron/__init__.py
vfxwindow/natron/application.py
vfxwindow/natron/gui.py
vfxwindow/nuke/__init__.py
vfxwindow/nuke/application.py
vfxwindow/nuke/callbacks.py
vfxwindow/nuke/gui.py
vfxwindow/palettes/Houdini.17.json
vfxwindow/palettes/Houdini.18.json
vfxwindow/palettes/Katana.7.json
vfxwindow/palettes/Max.2020.json
vfxwindow/palettes/Maya.2015.json
vfxwindow/palettes/Maya.2016.json
vfxwindow/palettes/Maya.2017.json
vfxwindow/palettes/Maya.2018.json
vfxwindow/palettes/Maya.2020.json
vfxwindow/palettes/Maya.2022.json
vfxwindow/palettes/Nuke.10.json
vfxwindow/palettes/Nuke.11.json
vfxwindow/palettes/Nuke.12.json
vfxwindow/palettes/Nuke.9.json
vfxwindow/palettes/Qt.4.json
vfxwindow/palettes/Qt.5.json
vfxwindow/renderdoc/__init__.py
vfxwindow/renderdoc/application.py
vfxwindow/renderdoc/gui.py
vfxwindow/standalone/__init__.py
vfxwindow/standalone/gui.py
vfxwindow/substance_designer/__init__.py
