Metadata-Version: 2.4
Name: vfxwindow
Version: 1.10.0
Summary: Qt window class for designing tools to be compatible between multiple VFX programs.
Home-page: https://github.com/huntfx/vfxwindow
Download-URL: https://github.com/huntfx/vfxwindow/archive/1.10.0.tar.gz
Author: Peter Hunt
Author-email: peter@huntfx.uk
License: MIT
Project-URL: Documentation, https://github.com/huntfx/vfxwindow/wiki
Project-URL: Source, https://github.com/huntfx/vfxwindow
Project-URL: Issues, https://github.com/huntfx/vfxwindow/issues
Keywords: qt,pyside,pyside2,pyqt,pyqt4,pyqt5,gui,window,maya,mayapy,nuke,nukescripts,houdini,unreal,engine,ue4,blender,3dsmax,3ds,blackmagic,fusion,substance,designer,vfx,visualfx,fx,cgi,3d,natron
Classifier: Development Status :: 4 - Beta
Classifier: Intended Audience :: Developers
Classifier: License :: OSI Approved :: MIT License
Classifier: Operating System :: Microsoft :: Windows
Classifier: Operating System :: POSIX :: Linux
Classifier: Programming Language :: Python
Classifier: Programming Language :: Python :: 2
Classifier: Programming Language :: Python :: 2.7
Classifier: Programming Language :: Python :: 3
Classifier: Programming Language :: Python :: 3.4
Classifier: Programming Language :: Python :: 3.5
Classifier: Programming Language :: Python :: 3.6
Classifier: Programming Language :: Python :: 3.7
Classifier: Programming Language :: Python :: 3.8
Classifier: Topic :: Multimedia :: Graphics :: 3D Modeling
Classifier: Topic :: Multimedia :: Graphics :: 3D Rendering
Classifier: Topic :: Software Development :: User Interfaces
Requires-Python: >=2.7, !=3.0.*, !=3.1.*, !=3.2.*
License-File: LICENSE
Requires-Dist: Qt.py
Dynamic: author
Dynamic: author-email
Dynamic: classifier
Dynamic: description
Dynamic: description-content-type
Dynamic: download-url
Dynamic: home-page
Dynamic: keywords
Dynamic: license
Dynamic: license-file
Dynamic: project-url
Dynamic: requires-dist
Dynamic: requires-python
Dynamic: summary
